{"game_id": "101342", "country": "us", "data": [{"region": "Pennsylvania", "min": 54, "max": 78, "coverage": 37.5, "n_users": 3}, {"region": "Pennsylvania", "min": 65, "max": 94, "coverage": 25.0, "n_users": 2}, {"region": "Pennsylvania", "min": 36, "max": 59, "coverage": 12.5, "n_users": 1}, {"region": "Pennsylvania", "min": 84, "max": 97, "coverage": 12.5, "n_users": 1}, {"region": "Pennsylvania", "min": 124, "max": 142, "coverage": 12.5, "n_users": 1}, {"region": "Massachusetts", "min": 59, "max": 84, "coverage": 100.0, "n_users": 2}, {"region": "Virginia", "min": 115, "max": 126, "coverage": 50.0, "n_users": 1}, {"region": "Virginia", "min": 38, "max": 59, "coverage": 50.0, "n_users": 1}, {"region": "Ohio", "min": 47, "max": 77, "coverage": 60.0, "n_users": 3}, {"region": "Ohio", "min": 77, "max": 99, "coverage": 20.0, "n_users": 1}, {"region": "Ohio", "min": 66, "max": 83, "coverage": 20.0, "n_users": 1}, {"region": "Oklahoma", "min": 53, "max": 57, "coverage": 100.0, "n_users": 1}, {"region": "Nevada", "min": 95, "max": 119, "coverage": 40.0, "n_users": 2}, {"region": "Nevada", "min": 46, "max": 66, "coverage": 40.0, "n_users": 2}, {"region": "Nevada", "min": 58, "max": 80, "coverage": 20.0, "n_users": 1}, {"region": "Oregon", "min": 54, "max": 69, "coverage": 66.66666666666667, "n_users": 2}, {"region": "Oregon", "min": 76, "max": 87, "coverage": 33.333333333333336, "n_users": 1}, {"region": "Georgia", "min": 98, "max": 112, "coverage": 33.333333333333336, "n_users": 1}, {"region": "Georgia", "min": 43, "max": 65, "coverage": 33.333333333333336, "n_users": 1}, {"region": "Georgia", "min": 56, "max": 83, "coverage": 33.333333333333336, "n_users": 1}, {"region": "North Carolina", "min": 54, "max": 84, "coverage": 100.0, "n_users": 1}, {"region": "Arizona", "min": 76, "max": 99, "coverage": 50.0, "n_users": 1}, {"region": "Arizona", "min": 63, "max": 76, "coverage": 50.0, "n_users": 1}, {"region": "Iowa", "min": 39, "max": 67, "coverage": 100.0, "n_users": 2}, {"region": "Missouri", "min": 51, "max": 72, "coverage": 50.0, "n_users": 1}, {"region": "Missouri", "min": 67, "max": 96, "coverage": 50.0, "n_users": 1}, {"region": "Nebraska", "min": 99, "max": 115, "coverage": 100.0, "n_users": 1}, {"region": "Colorado", "min": 63, "max": 77, "coverage": 100.0, "n_users": 1}, {"region": "Alaska", "min": 72, "max": 101, "coverage": 100.0, "n_users": 2}, {"region": "Illinois", "min": 34, "max": 58, "coverage": 50.0, "n_users": 1}, {"region": "Illinois", "min": 39, "max": 66, "coverage": 50.0, "n_users": 1}, {"region": "Hawaii", "min": 53, "max": 73, "coverage": 50.0, "n_users": 1}, {"region": "Hawaii", "min": 233, "max": 256, "coverage": 50.0, "n_users": 1}, {"region": "Kansas", "min": 52, "max": 70, "coverage": 100.0, "n_users": 1}, {"region": "Utah", "min": 40, "max": 51, "coverage": 100.0, "n_users": 1}, {"region": "Louisiana", "min": 73, "max": 85, "coverage": 100.0, "n_users": 1}, {"region": "Idaho", "min": 61, "max": 81, "coverage": 100.0, "n_users": 1}, {"region": "New Jersey", "min": 32, "max": 49, "coverage": 100.0, "n_users": 1}, {"region": "Florida", "min": 57, "max": 78, "coverage": 50.0, "n_users": 1}, {"region": "Florida", "min": 108, "max": 133, "coverage": 50.0, "n_users": 1}, {"region": "Connecticut", "min": 54, "max": 69, "coverage": 100.0, "n_users": 1}, {"region": "Wisconsin", "min": 34, "max": 59, "coverage": 100.0, "n_users": 1}, {"region": "Minnesota", "min": 43, "max": 72, "coverage": 100.0, "n_users": 3}, {"region": "Indiana", "min": 34, "max": 61, "coverage": 66.66666666666667, "n_users": 2}, {"region": "Indiana", "min": 43, "max": 71, "coverage": 33.333333333333336, "n_users": 1}, {"region": "Maryland", "min": 38, "max": 52, "coverage": 100.0, "n_users": 1}, {"region": "South Carolina", "min": 51, "max": 76, "coverage": 100.0, "n_users": 1}, {"region": "Washington", "min": 49, "max": 61, "coverage": 50.0, "n_users": 1}, {"region": "Washington", "min": 132, "max": 146, "coverage": 50.0, "n_users": 1}, {"region": "Montana", "min": 62, "max": 89, "coverage": 100.0, "n_users": 1}, {"region": "Texas", "min": 49, "max": 78, "coverage": 72.72727272727273, "n_users": 8}, {"region": "Texas", "min": 36, "max": 56, "coverage": 18.181818181818183, "n_users": 2}, {"region": "Texas", "min": 54, "max": 81, "coverage": 9.090909090909092, "n_users": 1}, {"region": "New York", "min": 58, "max": 87, "coverage": 50.0, "n_users": 2}, {"region": "New York", "min": 35, "max": 58, "coverage": 50.0, "n_users": 2}, {"region": "Michigan", "min": 42, "max": 70, "coverage": 66.66666666666667, "n_users": 4}, {"region": "Michigan", "min": 55, "max": 84, "coverage": 33.333333333333336, "n_users": 2}, {"region": "Tennessee", "min": 54, "max": 74, "coverage": 100.0, "n_users": 1}, {"region": "California", "min": 47, "max": 73, "coverage": 66.66666666666667, "n_users": 6}, {"region": "California", "min": 194, "max": 208, "coverage": 11.11111111111111, "n_users": 1}, {"region": "California", "min": 39, "max": 56, "coverage": 11.11111111111111, "n_users": 1}, {"region": "California", "min": 65, "max": 79, "coverage": 11.11111111111111, "n_users": 1}], "last_updated": 1698029236.86287}