{"game_id": "101342", "country": "gb", "data": [{"region": "2641364", "min": 38, "max": 48, "coverage": 100.0, "n_users": 1}, {"region": "2638360", "min": 48, "max": 76, "coverage": 42.857142857142854, "n_users": 3}, {"region": "2638360", "min": 68, "max": 84, "coverage": 28.571428571428573, "n_users": 2}, {"region": "2638360", "min": 42, "max": 72, "coverage": 28.571428571428573, "n_users": 2}, {"region": "6269131", "min": 43, "max": 70, "coverage": 29.26829268292683, "n_users": 12}, {"region": "6269131", "min": 29, "max": 58, "coverage": 24.390243902439025, "n_users": 10}, {"region": "6269131", "min": 35, "max": 63, "coverage": 21.951219512195124, "n_users": 9}, {"region": "6269131", "min": 50, "max": 79, "coverage": 9.75609756097561, "n_users": 4}, {"region": "6269131", "min": 73, "max": 90, "coverage": 4.878048780487805, "n_users": 2}, {"region": "6269131", "min": 139, "max": 153, "coverage": 2.4390243902439024, "n_users": 1}, {"region": "6269131", "min": 6, "max": 8, "coverage": 2.4390243902439024, "n_users": 1}, {"region": "6269131", "min": 157, "max": 174, "coverage": 2.4390243902439024, "n_users": 1}, {"region": "6269131", "min": 83, "max": 112, "coverage": 2.4390243902439024, "n_users": 1}, {"region": "2634895", "min": 45, "max": 72, "coverage": 50.0, "n_users": 1}, {"region": "2634895", "min": 40, "max": 70, "coverage": 50.0, "n_users": 1}], "last_updated": 1740737245.226564}