{"game_id": "118849", "country": "gb", "data": [{"region": "Scotland", "min": 24, "max": 48, "coverage": 50.0, "n_users": 12}, {"region": "Scotland", "min": 15, "max": 41, "coverage": 37.5, "n_users": 9}, {"region": "Scotland", "min": 5, "max": 8, "coverage": 4.166666666666667, "n_users": 1}, {"region": "Scotland", "min": 50, "max": 73, "coverage": 4.166666666666667, "n_users": 1}, {"region": "Scotland", "min": 100, "max": 106, "coverage": 4.166666666666667, "n_users": 1}, {"region": "England", "min": 7, "max": 37, "coverage": 59.76331360946745, "n_users": 101}, {"region": "England", "min": 12, "max": 42, "coverage": 18.34319526627219, "n_users": 31}, {"region": "England", "min": 28, "max": 56, "coverage": 7.100591715976331, "n_users": 12}, {"region": "England", "min": 87, "max": 116, "coverage": 4.733727810650888, "n_users": 8}, {"region": "England", "min": 1, "max": 26, "coverage": 4.1420118343195265, "n_users": 7}, {"region": "England", "min": 112, "max": 137, "coverage": 1.7751479289940828, "n_users": 3}, {"region": "England", "min": 146, "max": 168, "coverage": 1.183431952662722, "n_users": 2}, {"region": "England", "min": 43, "max": 66, "coverage": 1.183431952662722, "n_users": 2}, {"region": "England", "min": 58, "max": 79, "coverage": 0.591715976331361, "n_users": 1}, {"region": "England", "min": 830, "max": 845, "coverage": 0.591715976331361, "n_users": 1}, {"region": "England", "min": 21, "max": 43, "coverage": 0.591715976331361, "n_users": 1}, {"region": "Northern Ireland", "min": 24, "max": 40, "coverage": 80.0, "n_users": 4}, {"region": "Northern Ireland", "min": 1, "max": 5, "coverage": 20.0, "n_users": 1}, {"region": "Cymru / Wales", "min": 13, "max": 40, "coverage": 66.66666666666667, "n_users": 8}, {"region": "Cymru / Wales", "min": 6, "max": 29, "coverage": 25.0, "n_users": 3}, {"region": "Cymru / Wales", "min": 101, "max": 102, "coverage": 8.333333333333334, "n_users": 1}], "last_updated": 1702668484.648851}