{"game_id": "118849", "country": "nl", "data": [{"region": "2749879", "min": 1, "max": 21, "coverage": 83.33333333333333, "n_users": 5}, {"region": "2749879", "min": 98, "max": 102, "coverage": 16.666666666666668, "n_users": 1}, {"region": "2749990", "min": 1, "max": 22, "coverage": 100.0, "n_users": 4}, {"region": "2755249", "min": 13, "max": 30, "coverage": 75.0, "n_users": 3}, {"region": "2755249", "min": 186, "max": 189, "coverage": 25.0, "n_users": 1}, {"region": "2745909", "min": 2, "max": 2, "coverage": 100.0, "n_users": 1}, {"region": "2755634", "min": 2, "max": 6, "coverage": 100.0, "n_users": 1}, {"region": "2744011", "min": 12, "max": 17, "coverage": 100.0, "n_users": 1}, {"region": "3319179", "min": 10, "max": 11, "coverage": 100.0, "n_users": 1}, {"region": "2748838", "min": 1, "max": 14, "coverage": 100.0, "n_users": 1}, {"region": "2755812", "min": 11, "max": 19, "coverage": 100.0, "n_users": 1}, {"region": "2756631", "min": 11, "max": 13, "coverage": 100.0, "n_users": 1}, {"region": "2743698", "min": 1, "max": 29, "coverage": 100.0, "n_users": 3}], "last_updated": 1721709564.485937}