{"game_id": "118849", "country": "ca", "data": [{"region": "6141242", "min": 33, "max": 63, "coverage": 71.42857142857143, "n_users": 5}, {"region": "6141242", "min": 30, "max": 44, "coverage": 28.571428571428573, "n_users": 2}, {"region": "6091530", "min": 89, "max": 98, "coverage": 40.0, "n_users": 2}, {"region": "6091530", "min": 37, "max": 64, "coverage": 40.0, "n_users": 2}, {"region": "6091530", "min": 57, "max": 80, "coverage": 20.0, "n_users": 1}, {"region": "6091732", "min": 20, "max": 30, "coverage": 100.0, "n_users": 1}, {"region": "6113358", "min": 45, "max": 62, "coverage": 100.0, "n_users": 1}, {"region": "6354959", "min": 50, "max": 78, "coverage": 100.0, "n_users": 4}, {"region": "5883102", "min": 31, "max": 61, "coverage": 50.0, "n_users": 14}, {"region": "5883102", "min": 50, "max": 78, "coverage": 39.285714285714285, "n_users": 11}, {"region": "5883102", "min": 64, "max": 91, "coverage": 7.142857142857143, "n_users": 2}, {"region": "5883102", "min": 23, "max": 33, "coverage": 3.5714285714285716, "n_users": 1}, {"region": "6115047", "min": 19, "max": 46, "coverage": 70.6896551724138, "n_users": 41}, {"region": "6115047", "min": 21, "max": 50, "coverage": 13.793103448275861, "n_users": 8}, {"region": "6115047", "min": 80, "max": 103, "coverage": 5.172413793103448, "n_users": 3}, {"region": "6115047", "min": 69, "max": 95, "coverage": 5.172413793103448, "n_users": 3}, {"region": "6115047", "min": 1, "max": 22, "coverage": 5.172413793103448, "n_users": 3}, {"region": "5909050", "min": 46, "max": 76, "coverage": 72.36842105263158, "n_users": 55}, {"region": "5909050", "min": 1, "max": 30, "coverage": 10.526315789473685, "n_users": 8}, {"region": "5909050", "min": 71, "max": 93, "coverage": 6.578947368421052, "n_users": 5}, {"region": "5909050", "min": 32, "max": 61, "coverage": 6.578947368421052, "n_users": 5}, {"region": "5909050", "min": 50, "max": 78, "coverage": 2.6315789473684212, "n_users": 2}, {"region": "5909050", "min": 26, "max": 38, "coverage": 1.3157894736842106, "n_users": 1}, {"region": "6065171", "min": 53, "max": 66, "coverage": 50.0, "n_users": 2}, {"region": "6065171", "min": 58, "max": 87, "coverage": 25.0, "n_users": 1}, {"region": "6065171", "min": 25, "max": 39, "coverage": 25.0, "n_users": 1}, {"region": "6093943", "min": 12, "max": 42, "coverage": 45.65217391304348, "n_users": 63}, {"region": "6093943", "min": 1, "max": 27, "coverage": 20.28985507246377, "n_users": 28}, {"region": "6093943", "min": 22, "max": 51, "coverage": 13.768115942028986, "n_users": 19}, {"region": "6093943", "min": 41, "max": 71, "coverage": 6.521739130434782, "n_users": 9}, {"region": "6093943", "min": 37, "max": 65, "coverage": 4.3478260869565215, "n_users": 6}, {"region": "6093943", "min": 73, "max": 101, "coverage": 2.898550724637681, "n_users": 4}, {"region": "6093943", "min": 120, "max": 143, "coverage": 1.4492753623188406, "n_users": 2}, {"region": "6093943", "min": 104, "max": 119, "coverage": 1.4492753623188406, "n_users": 2}, {"region": "6093943", "min": 25, "max": 53, "coverage": 0.7246376811594203, "n_users": 1}, {"region": "6093943", "min": 193, "max": 193, "coverage": 0.7246376811594203, "n_users": 1}, {"region": "6093943", "min": 7, "max": 33, "coverage": 0.7246376811594203, "n_users": 1}, {"region": "6093943", "min": 515, "max": 515, "coverage": 0.7246376811594203, "n_users": 1}, {"region": "6093943", "min": 20, "max": 44, "coverage": 0.7246376811594203, "n_users": 1}], "last_updated": 1732167791.766077}