{"game_id": "128974", "country": "au", "data": [{"region": "2147291", "min": 28, "max": 52, "coverage": 100.0, "n_users": 3}, {"region": "21674637", "min": 24, "max": 40, "coverage": 50.0, "n_users": 1}, {"region": "21674637", "min": 226, "max": 229, "coverage": 50.0, "n_users": 1}, {"region": "2152274", "min": 33, "max": 58, "coverage": 54.54545454545455, "n_users": 18}, {"region": "2152274", "min": 21, "max": 44, "coverage": 39.39393939393939, "n_users": 13}, {"region": "2152274", "min": 51, "max": 70, "coverage": 3.0303030303030303, "n_users": 1}, {"region": "2152274", "min": 4, "max": 9, "coverage": 3.0303030303030303, "n_users": 1}, {"region": "2061327", "min": 40, "max": 68, "coverage": 50.0, "n_users": 9}, {"region": "2061327", "min": 23, "max": 47, "coverage": 33.333333333333336, "n_users": 6}, {"region": "2061327", "min": 50, "max": 79, "coverage": 16.666666666666668, "n_users": 3}, {"region": "2058645", "min": 50, "max": 80, "coverage": 65.0, "n_users": 13}, {"region": "2058645", "min": 72, "max": 99, "coverage": 25.0, "n_users": 5}, {"region": "2058645", "min": 24, "max": 46, "coverage": 5.0, "n_users": 1}, {"region": "2058645", "min": 108, "max": 127, "coverage": 5.0, "n_users": 1}, {"region": "2155400", "min": 16, "max": 46, "coverage": 69.11764705882354, "n_users": 47}, {"region": "2155400", "min": 3, "max": 32, "coverage": 17.647058823529413, "n_users": 12}, {"region": "2155400", "min": 23, "max": 49, "coverage": 4.411764705882353, "n_users": 3}, {"region": "2155400", "min": 151, "max": 173, "coverage": 2.9411764705882355, "n_users": 2}, {"region": "2155400", "min": 58, "max": 87, "coverage": 2.9411764705882355, "n_users": 2}, {"region": "2155400", "min": 85, "max": 91, "coverage": 1.4705882352941178, "n_users": 1}, {"region": "2155400", "min": 37, "max": 59, "coverage": 1.4705882352941178, "n_users": 1}, {"region": "2145234", "min": 23, "max": 53, "coverage": 82.05128205128206, "n_users": 64}, {"region": "2145234", "min": 36, "max": 66, "coverage": 7.6923076923076925, "n_users": 6}, {"region": "2145234", "min": 15, "max": 41, "coverage": 6.410256410256411, "n_users": 5}, {"region": "2145234", "min": 79, "max": 92, "coverage": 1.2820512820512822, "n_users": 1}, {"region": "2145234", "min": 224, "max": 232, "coverage": 1.2820512820512822, "n_users": 1}, {"region": "2145234", "min": 32, "max": 56, "coverage": 1.2820512820512822, "n_users": 1}], "last_updated": 1733415815.14163}