{"game_id": "128974", "country": "gb", "data": [{"region": "2634895", "min": 22, "max": 51, "coverage": 92.3076923076923, "n_users": 24}, {"region": "2634895", "min": 57, "max": 71, "coverage": 7.6923076923076925, "n_users": 2}, {"region": "2638360", "min": 25, "max": 54, "coverage": 67.79661016949153, "n_users": 40}, {"region": "2638360", "min": 40, "max": 64, "coverage": 16.949152542372882, "n_users": 10}, {"region": "2638360", "min": 19, "max": 46, "coverage": 5.084745762711864, "n_users": 3}, {"region": "2638360", "min": 29, "max": 57, "coverage": 5.084745762711864, "n_users": 3}, {"region": "2638360", "min": 120, "max": 127, "coverage": 3.389830508474576, "n_users": 2}, {"region": "2638360", "min": 1, "max": 3, "coverage": 1.694915254237288, "n_users": 1}, {"region": "2641364", "min": 25, "max": 53, "coverage": 81.25, "n_users": 13}, {"region": "2641364", "min": 44, "max": 62, "coverage": 12.5, "n_users": 2}, {"region": "2641364", "min": 76, "max": 97, "coverage": 6.25, "n_users": 1}, {"region": "6269131", "min": 19, "max": 49, "coverage": 74.19354838709677, "n_users": 230}, {"region": "6269131", "min": 10, "max": 40, "coverage": 7.741935483870968, "n_users": 24}, {"region": "6269131", "min": 37, "max": 67, "coverage": 7.096774193548387, "n_users": 22}, {"region": "6269131", "min": 32, "max": 57, "coverage": 5.161290322580645, "n_users": 16}, {"region": "6269131", "min": 86, "max": 114, "coverage": 1.2903225806451613, "n_users": 4}, {"region": "6269131", "min": 44, "max": 68, "coverage": 0.967741935483871, "n_users": 3}, {"region": "6269131", "min": 24, "max": 51, "coverage": 0.967741935483871, "n_users": 3}, {"region": "6269131", "min": 61, "max": 91, "coverage": 0.967741935483871, "n_users": 3}, {"region": "6269131", "min": 113, "max": 139, "coverage": 0.6451612903225806, "n_users": 2}, {"region": "6269131", "min": 2, "max": 7, "coverage": 0.3225806451612903, "n_users": 1}, {"region": "6269131", "min": 133, "max": 156, "coverage": 0.3225806451612903, "n_users": 1}, {"region": "6269131", "min": 108, "max": 118, "coverage": 0.3225806451612903, "n_users": 1}], "last_updated": 1739549415.332589}