{"game_id": "295590", "country": "ca", "data": [{"region": "6065171", "min": 24, "max": 52, "coverage": 79.41176470588235, "n_users": 27}, {"region": "6065171", "min": 7, "max": 36, "coverage": 11.764705882352942, "n_users": 4}, {"region": "6065171", "min": 48, "max": 75, "coverage": 2.9411764705882355, "n_users": 1}, {"region": "6065171", "min": 148, "max": 150, "coverage": 2.9411764705882355, "n_users": 1}, {"region": "6065171", "min": 37, "max": 56, "coverage": 2.9411764705882355, "n_users": 1}, {"region": "6093943", "min": 20, "max": 50, "coverage": 41.45985401459854, "n_users": 284}, {"region": "6093943", "min": 9, "max": 39, "coverage": 32.99270072992701, "n_users": 226}, {"region": "6093943", "min": 1, "max": 29, "coverage": 9.197080291970803, "n_users": 63}, {"region": "6093943", "min": 38, "max": 68, "coverage": 4.671532846715328, "n_users": 32}, {"region": "6093943", "min": 24, "max": 54, "coverage": 3.3576642335766422, "n_users": 23}, {"region": "6093943", "min": 12, "max": 42, "coverage": 2.0437956204379564, "n_users": 14}, {"region": "6093943", "min": 22, "max": 52, "coverage": 1.0218978102189782, "n_users": 7}, {"region": "6093943", "min": 28, "max": 58, "coverage": 0.8759124087591241, "n_users": 6}, {"region": "6093943", "min": 33, "max": 63, "coverage": 0.8759124087591241, "n_users": 6}, {"region": "6093943", "min": 138, "max": 166, "coverage": 0.583941605839416, "n_users": 4}, {"region": "6093943", "min": 53, "max": 82, "coverage": 0.583941605839416, "n_users": 4}, {"region": "6093943", "min": 87, "max": 117, "coverage": 0.43795620437956206, "n_users": 3}, {"region": "6093943", "min": 26, "max": 56, "coverage": 0.291970802919708, "n_users": 2}, {"region": "6093943", "min": 23, "max": 53, "coverage": 0.291970802919708, "n_users": 2}, {"region": "6093943", "min": 16, "max": 43, "coverage": 0.291970802919708, "n_users": 2}, {"region": "6093943", "min": 21, "max": 51, "coverage": 0.291970802919708, "n_users": 2}, {"region": "6093943", "min": 253, "max": 283, "coverage": 0.145985401459854, "n_users": 1}, {"region": "6093943", "min": 25, "max": 55, "coverage": 0.145985401459854, "n_users": 1}, {"region": "6093943", "min": 42, "max": 69, "coverage": 0.145985401459854, "n_users": 1}, {"region": "6093943", "min": 32, "max": 60, "coverage": 0.145985401459854, "n_users": 1}, {"region": "6093943", "min": 19, "max": 48, "coverage": 0.145985401459854, "n_users": 1}, {"region": "6115047", "min": 19, "max": 49, "coverage": 55.45977011494253, "n_users": 193}, {"region": "6115047", "min": 9, "max": 38, "coverage": 34.195402298850574, "n_users": 119}, {"region": "6115047", "min": 27, "max": 57, "coverage": 4.022988505747127, "n_users": 14}, {"region": "6115047", "min": 1, "max": 24, "coverage": 1.7241379310344827, "n_users": 6}, {"region": "6115047", "min": 100, "max": 128, "coverage": 1.1494252873563218, "n_users": 4}, {"region": "6115047", "min": 52, "max": 80, "coverage": 0.8620689655172413, "n_users": 3}, {"region": "6115047", "min": 72, "max": 94, "coverage": 0.5747126436781609, "n_users": 2}, {"region": "6115047", "min": 17, "max": 44, "coverage": 0.5747126436781609, "n_users": 2}, {"region": "6115047", "min": 87, "max": 111, "coverage": 0.5747126436781609, "n_users": 2}, {"region": "6115047", "min": 21, "max": 51, "coverage": 0.28735632183908044, "n_users": 1}, {"region": "6115047", "min": 139, "max": 157, "coverage": 0.28735632183908044, "n_users": 1}, {"region": "6115047", "min": 185, "max": 193, "coverage": 0.28735632183908044, "n_users": 1}, {"region": "5883102", "min": 46, "max": 76, "coverage": 68.75, "n_users": 99}, {"region": "5883102", "min": 53, "max": 82, "coverage": 10.416666666666666, "n_users": 15}, {"region": "5883102", "min": 2, "max": 28, "coverage": 5.555555555555555, "n_users": 8}, {"region": "5883102", "min": 33, "max": 58, "coverage": 4.861111111111111, "n_users": 7}, {"region": "5883102", "min": 40, "max": 70, "coverage": 4.166666666666667, "n_users": 6}, {"region": "5883102", "min": 74, "max": 96, "coverage": 2.0833333333333335, "n_users": 3}, {"region": "5883102", "min": 62, "max": 92, "coverage": 2.0833333333333335, "n_users": 3}, {"region": "5883102", "min": 50, "max": 78, "coverage": 0.6944444444444444, "n_users": 1}, {"region": "5883102", "min": 138, "max": 146, "coverage": 0.6944444444444444, "n_users": 1}, {"region": "5883102", "min": 110, "max": 117, "coverage": 0.6944444444444444, "n_users": 1}, {"region": "5909050", "min": 46, "max": 76, "coverage": 77.53623188405797, "n_users": 214}, {"region": "5909050", "min": 39, "max": 66, "coverage": 8.695652173913043, "n_users": 24}, {"region": "5909050", "min": 59, "max": 82, "coverage": 4.7101449275362315, "n_users": 13}, {"region": "5909050", "min": 1, "max": 27, "coverage": 3.9855072463768115, "n_users": 11}, {"region": "5909050", "min": 68, "max": 98, "coverage": 3.6231884057971016, "n_users": 10}, {"region": "5909050", "min": 20, "max": 46, "coverage": 1.0869565217391304, "n_users": 3}, {"region": "5909050", "min": 149, "max": 156, "coverage": 0.36231884057971014, "n_users": 1}, {"region": "6087430", "min": 33, "max": 61, "coverage": 69.23076923076923, "n_users": 9}, {"region": "6087430", "min": 55, "max": 84, "coverage": 23.076923076923077, "n_users": 3}, {"region": "6087430", "min": 37, "max": 64, "coverage": 7.6923076923076925, "n_users": 1}, {"region": "6091530", "min": 32, "max": 62, "coverage": 84.375, "n_users": 27}, {"region": "6091530", "min": 25, "max": 51, "coverage": 6.25, "n_users": 2}, {"region": "6091530", "min": 54, "max": 75, "coverage": 6.25, "n_users": 2}, {"region": "6091530", "min": 14, "max": 15, "coverage": 3.125, "n_users": 1}, {"region": "6354959", "min": 48, "max": 75, "coverage": 91.66666666666667, "n_users": 11}, {"region": "6354959", "min": 87, "max": 96, "coverage": 8.333333333333334, "n_users": 1}, {"region": "6141242", "min": 21, "max": 51, "coverage": 73.6842105263158, "n_users": 14}, {"region": "6141242", "min": 36, "max": 57, "coverage": 26.31578947368421, "n_users": 5}, {"region": "6091732", "min": 19, "max": 31, "coverage": 100.0, "n_users": 1}, {"region": "6113358", "min": 40, "max": 60, "coverage": 100.0, "n_users": 2}, {"region": "6185811", "min": 61, "max": 70, "coverage": 100.0, "n_users": 1}], "last_updated": 1740840148.95622}