{"game_id": "314852", "country": "gb", "data": [{"region": "Cymru / Wales", "min": 35, "max": 63, "coverage": 83.33333333333333, "n_users": 5}, {"region": "Cymru / Wales", "min": 98, "max": 100, "coverage": 16.666666666666668, "n_users": 1}, {"region": "Northern Ireland", "min": 34, "max": 62, "coverage": 100.0, "n_users": 2}, {"region": "England", "min": 28, "max": 58, "coverage": 52.83018867924528, "n_users": 28}, {"region": "England", "min": 40, "max": 70, "coverage": 35.84905660377358, "n_users": 19}, {"region": "England", "min": 55, "max": 73, "coverage": 3.7735849056603774, "n_users": 2}, {"region": "England", "min": 83, "max": 105, "coverage": 3.7735849056603774, "n_users": 2}, {"region": "England", "min": 37, "max": 63, "coverage": 1.8867924528301887, "n_users": 1}, {"region": "England", "min": 500, "max": 504, "coverage": 1.8867924528301887, "n_users": 1}, {"region": "Scotland", "min": 46, "max": 76, "coverage": 50.0, "n_users": 8}, {"region": "Scotland", "min": 108, "max": 138, "coverage": 25.0, "n_users": 4}, {"region": "Scotland", "min": 131, "max": 140, "coverage": 6.25, "n_users": 1}, {"region": "Scotland", "min": 65, "max": 78, "coverage": 6.25, "n_users": 1}, {"region": "Scotland", "min": 38, "max": 44, "coverage": 6.25, "n_users": 1}, {"region": "Scotland", "min": 3, "max": 4, "coverage": 6.25, "n_users": 1}], "last_updated": 1697881889.607773}