{"game_id": "314852", "country": "us", "data": [{"region": "5001836", "min": 30, "max": 57, "coverage": 66.66666666666667, "n_users": 20}, {"region": "5001836", "min": 42, "max": 72, "coverage": 20.0, "n_users": 6}, {"region": "5001836", "min": 73, "max": 93, "coverage": 6.666666666666667, "n_users": 2}, {"region": "5001836", "min": 25, "max": 40, "coverage": 3.3333333333333335, "n_users": 1}, {"region": "5001836", "min": 142, "max": 159, "coverage": 3.3333333333333335, "n_users": 1}, {"region": "4436296", "min": 49, "max": 76, "coverage": 50.0, "n_users": 4}, {"region": "4436296", "min": 75, "max": 94, "coverage": 37.5, "n_users": 3}, {"region": "4436296", "min": 40, "max": 51, "coverage": 12.5, "n_users": 1}, {"region": "4896861", "min": 42, "max": 68, "coverage": 54.83870967741935, "n_users": 34}, {"region": "4896861", "min": 29, "max": 59, "coverage": 14.516129032258064, "n_users": 9}, {"region": "4896861", "min": 61, "max": 83, "coverage": 8.064516129032258, "n_users": 5}, {"region": "4896861", "min": 1, "max": 29, "coverage": 4.838709677419355, "n_users": 3}, {"region": "4896861", "min": 52, "max": 73, "coverage": 4.838709677419355, "n_users": 3}, {"region": "4896861", "min": 68, "max": 94, "coverage": 4.838709677419355, "n_users": 3}, {"region": "4896861", "min": 115, "max": 145, "coverage": 3.225806451612903, "n_users": 2}, {"region": "4896861", "min": 19, "max": 42, "coverage": 3.225806451612903, "n_users": 2}, {"region": "4896861", "min": 34, "max": 61, "coverage": 1.6129032258064515, "n_users": 1}, {"region": "5815135", "min": 72, "max": 102, "coverage": 61.111111111111114, "n_users": 22}, {"region": "5815135", "min": 89, "max": 108, "coverage": 25.0, "n_users": 9}, {"region": "5815135", "min": 2, "max": 16, "coverage": 5.555555555555555, "n_users": 2}, {"region": "5815135", "min": 109, "max": 128, "coverage": 2.7777777777777777, "n_users": 1}, {"region": "5815135", "min": 46, "max": 52, "coverage": 2.7777777777777777, "n_users": 1}, {"region": "5815135", "min": 170, "max": 175, "coverage": 2.7777777777777777, "n_users": 1}, {"region": "5101760", "min": 17, "max": 47, "coverage": 48.78048780487805, "n_users": 20}, {"region": "5101760", "min": 3, "max": 33, "coverage": 31.70731707317073, "n_users": 13}, {"region": "5101760", "min": 30, "max": 60, "coverage": 14.634146341463415, "n_users": 6}, {"region": "5101760", "min": 77, "max": 81, "coverage": 2.4390243902439024, "n_users": 1}, {"region": "5101760", "min": 16, "max": 41, "coverage": 2.4390243902439024, "n_users": 1}, {"region": "5128638", "min": 19, "max": 49, "coverage": 57.35294117647059, "n_users": 78}, {"region": "5128638", "min": 44, "max": 73, "coverage": 12.5, "n_users": 17}, {"region": "5128638", "min": 13, "max": 38, "coverage": 8.823529411764707, "n_users": 12}, {"region": "5128638", "min": 37, "max": 65, "coverage": 8.088235294117647, "n_users": 11}, {"region": "5128638", "min": 1, "max": 28, "coverage": 6.617647058823529, "n_users": 9}, {"region": "5128638", "min": 69, "max": 78, "coverage": 2.2058823529411766, "n_users": 3}, {"region": "5128638", "min": 178, "max": 207, "coverage": 1.4705882352941178, "n_users": 2}, {"region": "5128638", "min": 97, "max": 118, "coverage": 1.4705882352941178, "n_users": 2}, {"region": "5128638", "min": 155, "max": 157, "coverage": 0.7352941176470589, "n_users": 1}, {"region": "5128638", "min": 30, "max": 54, "coverage": 0.7352941176470589, "n_users": 1}, {"region": "4736286", "min": 44, "max": 74, "coverage": 45.08670520231214, "n_users": 78}, {"region": "4736286", "min": 63, "max": 93, "coverage": 18.497109826589597, "n_users": 32}, {"region": "4736286", "min": 25, "max": 55, "coverage": 9.826589595375722, "n_users": 17}, {"region": "4736286", "min": 52, "max": 82, "coverage": 8.092485549132949, "n_users": 14}, {"region": "4736286", "min": 1, "max": 25, "coverage": 4.624277456647399, "n_users": 8}, {"region": "4736286", "min": 40, "max": 63, "coverage": 4.624277456647399, "n_users": 8}, {"region": "4736286", "min": 59, "max": 88, "coverage": 2.8901734104046244, "n_users": 5}, {"region": "4736286", "min": 77, "max": 103, "coverage": 2.3121387283236996, "n_users": 4}, {"region": "4736286", "min": 97, "max": 119, "coverage": 1.7341040462427746, "n_users": 3}, {"region": "4736286", "min": 108, "max": 137, "coverage": 1.1560693641618498, "n_users": 2}, {"region": "4736286", "min": 56, "max": 86, "coverage": 0.5780346820809249, "n_users": 1}, {"region": "4736286", "min": 265, "max": 277, "coverage": 0.5780346820809249, "n_users": 1}, {"region": "4197000", "min": 30, "max": 59, "coverage": 59.45945945945946, "n_users": 22}, {"region": "4197000", "min": 56, "max": 84, "coverage": 10.81081081081081, "n_users": 4}, {"region": "4197000", "min": 80, "max": 109, "coverage": 8.108108108108109, "n_users": 3}, {"region": "4197000", "min": 23, "max": 53, "coverage": 8.108108108108109, "n_users": 3}, {"region": "4197000", "min": 50, "max": 68, "coverage": 5.405405405405405, "n_users": 2}, {"region": "4197000", "min": 4, "max": 4, "coverage": 2.7027027027027026, "n_users": 1}, {"region": "4197000", "min": 36, "max": 63, "coverage": 2.7027027027027026, "n_users": 1}, {"region": "4197000", "min": 22, "max": 41, "coverage": 2.7027027027027026, "n_users": 1}, {"region": "5332921", "min": 84, "max": 114, "coverage": 55.51470588235294, "n_users": 151}, {"region": "5332921", "min": 73, "max": 103, "coverage": 15.441176470588236, "n_users": 42}, {"region": "5332921", "min": 104, "max": 133, "coverage": 5.882352941176471, "n_users": 16}, {"region": "5332921", "min": 1, "max": 26, "coverage": 4.044117647058823, "n_users": 11}, {"region": "5332921", "min": 93, "max": 123, "coverage": 3.676470588235294, "n_users": 10}, {"region": "5332921", "min": 44, "max": 73, "coverage": 2.9411764705882355, "n_users": 8}, {"region": "5332921", "min": 63, "max": 87, "coverage": 2.573529411764706, "n_users": 7}, {"region": "5332921", "min": 136, "max": 157, "coverage": 1.1029411764705883, "n_users": 3}, {"region": "5332921", "min": 34, "max": 64, "coverage": 1.1029411764705883, "n_users": 3}, {"region": "5332921", "min": 167, "max": 191, "coverage": 1.1029411764705883, "n_users": 3}, {"region": "5332921", "min": 10, "max": 37, "coverage": 1.1029411764705883, "n_users": 3}, {"region": "5332921", "min": 87, "max": 117, "coverage": 1.1029411764705883, "n_users": 3}, {"region": "5332921", "min": 80, "max": 110, "coverage": 0.7352941176470589, "n_users": 2}, {"region": "5332921", "min": 78, "max": 108, "coverage": 0.7352941176470589, "n_users": 2}, {"region": "5332921", "min": 123, "max": 139, "coverage": 0.7352941176470589, "n_users": 2}, {"region": "5332921", "min": 98, "max": 127, "coverage": 0.7352941176470589, "n_users": 2}, {"region": "5332921", "min": 188, "max": 201, "coverage": 0.36764705882352944, "n_users": 1}, {"region": "5332921", "min": 72, "max": 100, "coverage": 0.36764705882352944, "n_users": 1}, {"region": "5332921", "min": 30, "max": 50, "coverage": 0.36764705882352944, "n_users": 1}, {"region": "5332921", "min": 108, "max": 135, "coverage": 0.36764705882352944, "n_users": 1}, {"region": "5843591", "min": 25, "max": 48, "coverage": 100.0, "n_users": 3}, {"region": "5744337", "min": 72, "max": 99, "coverage": 45.0, "n_users": 9}, {"region": "5744337", "min": 85, "max": 108, "coverage": 40.0, "n_users": 8}, {"region": "5744337", "min": 24, "max": 42, "coverage": 10.0, "n_users": 2}, {"region": "5744337", "min": 122, "max": 137, "coverage": 5.0, "n_users": 1}, {"region": "5417618", "min": 47, "max": 76, "coverage": 62.96296296296296, "n_users": 17}, {"region": "5417618", "min": 57, "max": 83, "coverage": 14.814814814814815, "n_users": 4}, {"region": "5417618", "min": 30, "max": 53, "coverage": 11.11111111111111, "n_users": 3}, {"region": "5417618", "min": 77, "max": 98, "coverage": 7.407407407407407, "n_users": 2}, {"region": "5417618", "min": 146, "max": 158, "coverage": 3.7037037037037037, "n_users": 1}, {"region": "4361885", "min": 12, "max": 40, "coverage": 80.76923076923077, "n_users": 21}, {"region": "4361885", "min": 31, "max": 57, "coverage": 19.23076923076923, "n_users": 5}, {"region": "4155751", "min": 49, "max": 78, "coverage": 42.857142857142854, "n_users": 51}, {"region": "4155751", "min": 29, "max": 59, "coverage": 29.41176470588235, "n_users": 35}, {"region": "4155751", "min": 41, "max": 71, "coverage": 12.605042016806722, "n_users": 15}, {"region": "4155751", "min": 62, "max": 91, "coverage": 5.042016806722689, "n_users": 6}, {"region": "4155751", "min": 39, "max": 68, "coverage": 3.361344537815126, "n_users": 4}, {"region": "4155751", "min": 5, "max": 35, "coverage": 2.5210084033613445, "n_users": 3}, {"region": "4155751", "min": 1, "max": 20, "coverage": 2.5210084033613445, "n_users": 3}, {"region": "4155751", "min": 87, "max": 97, "coverage": 0.8403361344537815, "n_users": 1}, {"region": "4155751", "min": 222, "max": 227, "coverage": 0.8403361344537815, "n_users": 1}, {"region": "5551752", "min": 79, "max": 109, "coverage": 50.0, "n_users": 20}, {"region": "5551752", "min": 60, "max": 87, "coverage": 12.5, "n_users": 5}, {"region": "5551752", "min": 26, "max": 52, "coverage": 10.0, "n_users": 4}, {"region": "5551752", "min": 68, "max": 98, "coverage": 10.0, "n_users": 4}, {"region": "5551752", "min": 5, "max": 10, "coverage": 5.0, "n_users": 2}, {"region": "5551752", "min": 42, "max": 65, "coverage": 5.0, "n_users": 2}, {"region": "5551752", "min": 83, "max": 111, "coverage": 2.5, "n_users": 1}, {"region": "5551752", "min": 216, "max": 225, "coverage": 2.5, "n_users": 1}, {"region": "5551752", "min": 52, "max": 74, "coverage": 2.5, "n_users": 1}, {"region": "4862182", "min": 15, "max": 33, "coverage": 37.5, "n_users": 3}, {"region": "4862182", "min": 57, "max": 71, "coverage": 25.0, "n_users": 2}, {"region": "4862182", "min": 82, "max": 99, "coverage": 25.0, "n_users": 2}, {"region": "4862182", "min": 131, "max": 135, "coverage": 12.5, "n_users": 1}, {"region": "6254927", "min": 17, "max": 47, "coverage": 50.0, "n_users": 23}, {"region": "6254927", "min": 39, "max": 68, "coverage": 30.434782608695652, "n_users": 14}, {"region": "6254927", "min": 35, "max": 53, "coverage": 8.695652173913043, "n_users": 4}, {"region": "6254927", "min": 85, "max": 110, "coverage": 4.3478260869565215, "n_users": 2}, {"region": "6254927", "min": 176, "max": 181, "coverage": 2.1739130434782608, "n_users": 1}, {"region": "6254927", "min": 13, "max": 27, "coverage": 2.1739130434782608, "n_users": 1}, {"region": "6254927", "min": 118, "max": 133, "coverage": 2.1739130434782608, "n_users": 1}, {"region": "5509151", "min": 82, "max": 110, "coverage": 51.851851851851855, "n_users": 14}, {"region": "5509151", "min": 67, "max": 92, "coverage": 22.22222222222222, "n_users": 6}, {"region": "5509151", "min": 117, "max": 133, "coverage": 14.814814814814815, "n_users": 4}, {"region": "5509151", "min": 32, "max": 61, "coverage": 7.407407407407407, "n_users": 2}, {"region": "5509151", "min": 2, "max": 9, "coverage": 3.7037037037037037, "n_users": 1}, {"region": "6254928", "min": 17, "max": 47, "coverage": 54.285714285714285, "n_users": 19}, {"region": "6254928", "min": 35, "max": 65, "coverage": 22.857142857142858, "n_users": 8}, {"region": "6254928", "min": 5, "max": 35, "coverage": 17.142857142857142, "n_users": 6}, {"region": "6254928", "min": 72, "max": 99, "coverage": 5.714285714285714, "n_users": 2}, {"region": "4662168", "min": 42, "max": 70, "coverage": 62.5, "n_users": 10}, {"region": "4662168", "min": 26, "max": 47, "coverage": 18.75, "n_users": 3}, {"region": "4662168", "min": 78, "max": 89, "coverage": 6.25, "n_users": 1}, {"region": "4662168", "min": 57, "max": 79, "coverage": 6.25, "n_users": 1}, {"region": "4662168", "min": 134, "max": 147, "coverage": 6.25, "n_users": 1}, {"region": "4831725", "min": 17, "max": 43, "coverage": 66.66666666666667, "n_users": 6}, {"region": "4831725", "min": 37, "max": 61, "coverage": 22.22222222222222, "n_users": 2}, {"region": "4831725", "min": 2, "max": 7, "coverage": 11.11111111111111, "n_users": 1}, {"region": "5690696", "min": 46, "max": 55, "coverage": 100.0, "n_users": 1}, {"region": "5855797", "min": 136, "max": 166, "coverage": 39.285714285714285, "n_users": 11}, {"region": "5855797", "min": 73, "max": 101, "coverage": 21.428571428571427, "n_users": 6}, {"region": "5855797", "min": 113, "max": 139, "coverage": 10.714285714285714, "n_users": 3}, {"region": "5855797", "min": 131, "max": 150, "coverage": 10.714285714285714, "n_users": 3}, {"region": "5855797", "min": 37, "max": 67, "coverage": 10.714285714285714, "n_users": 3}, {"region": "5855797", "min": 3, "max": 10, "coverage": 3.5714285714285716, "n_users": 1}, {"region": "5855797", "min": 194, "max": 210, "coverage": 3.5714285714285716, "n_users": 1}, {"region": "5165418", "min": 32, "max": 62, "coverage": 55.55555555555556, "n_users": 20}, {"region": "5165418", "min": 54, "max": 82, "coverage": 11.11111111111111, "n_users": 4}, {"region": "5165418", "min": 43, "max": 71, "coverage": 11.11111111111111, "n_users": 4}, {"region": "5165418", "min": 24, "max": 53, "coverage": 11.11111111111111, "n_users": 4}, {"region": "5165418", "min": 90, "max": 109, "coverage": 8.333333333333334, "n_users": 3}, {"region": "5165418", "min": 1, "max": 3, "coverage": 2.7777777777777777, "n_users": 1}, {"region": "4482348", "min": 18, "max": 48, "coverage": 47.22222222222222, "n_users": 17}, {"region": "4482348", "min": 41, "max": 71, "coverage": 25.0, "n_users": 9}, {"region": "4482348", "min": 1, "max": 23, "coverage": 11.11111111111111, "n_users": 4}, {"region": "4482348", "min": 29, "max": 54, "coverage": 11.11111111111111, "n_users": 4}, {"region": "4482348", "min": 59, "max": 89, "coverage": 5.555555555555555, "n_users": 2}, {"region": "4331987", "min": 53, "max": 81, "coverage": 57.142857142857146, "n_users": 8}, {"region": "4331987", "min": 68, "max": 98, "coverage": 21.428571428571427, "n_users": 3}, {"region": "4331987", "min": 21, "max": 25, "coverage": 7.142857142857143, "n_users": 1}, {"region": "4331987", "min": 42, "max": 58, "coverage": 7.142857142857143, "n_users": 1}, {"region": "4331987", "min": 133, "max": 144, "coverage": 7.142857142857143, "n_users": 1}, {"region": "4921868", "min": 41, "max": 70, "coverage": 70.0, "n_users": 14}, {"region": "4921868", "min": 37, "max": 67, "coverage": 15.0, "n_users": 3}, {"region": "4921868", "min": 43, "max": 73, "coverage": 15.0, "n_users": 3}, {"region": "4273857", "min": 54, "max": 82, "coverage": 75.0, "n_users": 6}, {"region": "4273857", "min": 78, "max": 97, "coverage": 12.5, "n_users": 1}, {"region": "4273857", "min": 263, "max": 278, "coverage": 12.5, "n_users": 1}, {"region": "5279468", "min": 32, "max": 59, "coverage": 52.94117647058823, "n_users": 9}, {"region": "5279468", "min": 51, "max": 80, "coverage": 41.1764705882353, "n_users": 7}, {"region": "5279468", "min": 87, "max": 101, "coverage": 5.882352941176471, "n_users": 1}, {"region": "5549030", "min": 61, "max": 87, "coverage": 75.0, "n_users": 6}, {"region": "5549030", "min": 88, "max": 109, "coverage": 12.5, "n_users": 1}, {"region": "5549030", "min": 72, "max": 95, "coverage": 12.5, "n_users": 1}, {"region": "4398678", "min": 39, "max": 67, "coverage": 70.0, "n_users": 7}, {"region": "4398678", "min": 63, "max": 89, "coverage": 30.0, "n_users": 3}, {"region": "4826850", "min": 19, "max": 43, "coverage": 66.66666666666667, "n_users": 4}, {"region": "4826850", "min": 47, "max": 64, "coverage": 33.333333333333336, "n_users": 2}, {"region": "5037779", "min": 48, "max": 78, "coverage": 63.63636363636363, "n_users": 7}, {"region": "5037779", "min": 35, "max": 50, "coverage": 27.272727272727273, "n_users": 3}, {"region": "5037779", "min": 96, "max": 110, "coverage": 9.090909090909092, "n_users": 1}, {"region": "4544379", "min": 47, "max": 73, "coverage": 75.0, "n_users": 3}, {"region": "4544379", "min": 76, "max": 80, "coverage": 25.0, "n_users": 1}, {"region": "4099753", "min": 69, "max": 98, "coverage": 62.5, "n_users": 5}, {"region": "4099753", "min": 45, "max": 70, "coverage": 37.5, "n_users": 3}, {"region": "4597040", "min": 20, "max": 49, "coverage": 37.5, "n_users": 3}, {"region": "4597040", "min": 34, "max": 61, "coverage": 37.5, "n_users": 3}, {"region": "4597040", "min": 1, "max": 2, "coverage": 12.5, "n_users": 1}, {"region": "4597040", "min": 51, "max": 72, "coverage": 12.5, "n_users": 1}, {"region": "4041468", "min": 191, "max": 205, "coverage": 100.0, "n_users": 1}, {"region": "4566966", "min": 69, "max": 99, "coverage": 38.46153846153846, "n_users": 5}, {"region": "4566966", "min": 44, "max": 65, "coverage": 23.076923076923077, "n_users": 3}, {"region": "4566966", "min": 85, "max": 105, "coverage": 15.384615384615385, "n_users": 2}, {"region": "4566966", "min": 1, "max": 7, "coverage": 15.384615384615385, "n_users": 2}, {"region": "4566966", "min": 32, "max": 45, "coverage": 7.6923076923076925, "n_users": 1}, {"region": "4971068", "min": 21, "max": 50, "coverage": 38.46153846153846, "n_users": 5}, {"region": "4971068", "min": 47, "max": 77, "coverage": 23.076923076923077, "n_users": 3}, {"region": "4971068", "min": 42, "max": 67, "coverage": 15.384615384615385, "n_users": 2}, {"region": "4971068", "min": 2, "max": 16, "coverage": 15.384615384615385, "n_users": 2}, {"region": "4971068", "min": 69, "max": 94, "coverage": 7.6923076923076925, "n_users": 1}, {"region": "5690763", "min": 57, "max": 80, "coverage": 100.0, "n_users": 2}, {"region": "4138106", "min": 79, "max": 107, "coverage": 62.5, "n_users": 15}, {"region": "4138106", "min": 15, "max": 40, "coverage": 20.833333333333332, "n_users": 5}, {"region": "4138106", "min": 76, "max": 95, "coverage": 8.333333333333334, "n_users": 2}, {"region": "4138106", "min": 125, "max": 141, "coverage": 4.166666666666667, "n_users": 1}, {"region": "4138106", "min": 3, "max": 8, "coverage": 4.166666666666667, "n_users": 1}, {"region": "6254926", "min": 23, "max": 53, "coverage": 53.333333333333336, "n_users": 16}, {"region": "6254926", "min": 31, "max": 60, "coverage": 16.666666666666668, "n_users": 5}, {"region": "6254926", "min": 90, "max": 105, "coverage": 6.666666666666667, "n_users": 2}, {"region": "6254926", "min": 22, "max": 36, "coverage": 6.666666666666667, "n_users": 2}, {"region": "6254926", "min": 53, "max": 70, "coverage": 6.666666666666667, "n_users": 2}, {"region": "6254926", "min": 2, "max": 2, "coverage": 3.3333333333333335, "n_users": 1}, {"region": "6254926", "min": 38, "max": 64, "coverage": 3.3333333333333335, "n_users": 1}, {"region": "6254926", "min": 70, "max": 87, "coverage": 3.3333333333333335, "n_users": 1}, {"region": "5090174", "min": 32, "max": 59, "coverage": 100.0, "n_users": 8}, {"region": "4829764", "min": 47, "max": 57, "coverage": 50.0, "n_users": 3}, {"region": "4829764", "min": 81, "max": 92, "coverage": 16.666666666666668, "n_users": 1}, {"region": "4829764", "min": 26, "max": 37, "coverage": 16.666666666666668, "n_users": 1}, {"region": "4829764", "min": 5, "max": 6, "coverage": 16.666666666666668, "n_users": 1}, {"region": "5879092", "min": 131, "max": 157, "coverage": 38.46153846153846, "n_users": 5}, {"region": "5879092", "min": 106, "max": 136, "coverage": 38.46153846153846, "n_users": 5}, {"region": "5879092", "min": 33, "max": 42, "coverage": 15.384615384615385, "n_users": 2}, {"region": "5879092", "min": 66, "max": 87, "coverage": 7.6923076923076925, "n_users": 1}, {"region": "5224323", "min": 31, "max": 60, "coverage": 100.0, "n_users": 2}, {"region": "5481136", "min": 59, "max": 87, "coverage": 50.0, "n_users": 3}, {"region": "5481136", "min": 74, "max": 104, "coverage": 33.333333333333336, "n_users": 2}, {"region": "5481136", "min": 103, "max": 115, "coverage": 16.666666666666668, "n_users": 1}, {"region": "4043988", "min": 200, "max": 211, "coverage": 50.0, "n_users": 2}, {"region": "4043988", "min": 49, "max": 52, "coverage": 25.0, "n_users": 1}, {"region": "4043988", "min": 212, "max": 235, "coverage": 25.0, "n_users": 1}, {"region": "5769223", "min": 29, "max": 58, "coverage": 50.0, "n_users": 2}, {"region": "5769223", "min": 69, "max": 86, "coverage": 50.0, "n_users": 2}, {"region": "5596512", "min": 72, "max": 93, "coverage": 50.0, "n_users": 2}, {"region": "5596512", "min": 107, "max": 132, "coverage": 50.0, "n_users": 2}, {"region": "6254925", "min": 37, "max": 67, "coverage": 100.0, "n_users": 7}, {"region": "5073708", "min": 38, "max": 53, "coverage": 100.0, "n_users": 1}, {"region": "5242283", "min": 55, "max": 62, "coverage": 100.0, "n_users": 1}, {"region": "4142224", "min": 20, "max": 33, "coverage": 100.0, "n_users": 2}, {"region": "5667009", "min": 28, "max": 39, "coverage": 100.0, "n_users": 2}], "last_updated": 1740693675.029687}