{"game_id": "319965", "country": "no", "data": [{"region": "Tr\u00f8ndelag", "min": 50, "max": 50, "coverage": 75.0, "n_users": 3}, {"region": "Tr\u00f8ndelag", "min": 200, "max": 200, "coverage": 25.0, "n_users": 1}, {"region": "Agder", "min": 50, "max": 50, "coverage": 100.0, "n_users": 1}, {"region": "Oslo", "min": 50, "max": 50, "coverage": 100.0, "n_users": 2}, {"region": "Viken", "min": 50, "max": 50, "coverage": 100.0, "n_users": 1}, {"region": "Akershus (tidligere)", "min": 50, "max": 50, "coverage": 100.0, "n_users": 1}, {"region": "Vestfold og Telemark", "min": 157, "max": 157, "coverage": 100.0, "n_users": 1}, {"region": "Svalbard", "min": 50, "max": 59, "coverage": 100.0, "n_users": 1}, {"region": "Nordland", "min": 50, "max": 61, "coverage": 100.0, "n_users": 1}, {"region": "Rogaland", "min": 50, "max": 50, "coverage": 100.0, "n_users": 1}], "last_updated": 1709006018.880895}