{"game_id": "970338", "country": "us", "data": [{"region": "5879092", "min": 114, "max": 136, "coverage": 100.0, "n_users": 2}, {"region": "4398678", "min": 33, "max": 61, "coverage": 100.0, "n_users": 2}, {"region": "6254928", "min": 17, "max": 35, "coverage": 100.0, "n_users": 1}, {"region": "5224323", "min": 27, "max": 37, "coverage": 100.0, "n_users": 1}, {"region": "5549030", "min": 75, "max": 81, "coverage": 100.0, "n_users": 1}, {"region": "4544379", "min": 43, "max": 57, "coverage": 100.0, "n_users": 1}, {"region": "4831725", "min": 42, "max": 62, "coverage": 100.0, "n_users": 1}, {"region": "5769223", "min": 63, "max": 74, "coverage": 100.0, "n_users": 1}, {"region": "6254926", "min": 35, "max": 48, "coverage": 100.0, "n_users": 1}, {"region": "5815135", "min": 168, "max": 177, "coverage": 100.0, "n_users": 1}, {"region": "4436296", "min": 47, "max": 69, "coverage": 100.0, "n_users": 1}, {"region": "5509151", "min": 72, "max": 91, "coverage": 100.0, "n_users": 3}, {"region": "4597040", "min": 26, "max": 45, "coverage": 100.0, "n_users": 1}, {"region": "5855797", "min": 24, "max": 28, "coverage": 50.0, "n_users": 1}, {"region": "5855797", "min": 62, "max": 75, "coverage": 50.0, "n_users": 1}, {"region": "5744337", "min": 83, "max": 100, "coverage": 66.66666666666667, "n_users": 4}, {"region": "5744337", "min": 52, "max": 61, "coverage": 16.666666666666668, "n_users": 1}, {"region": "5744337", "min": 134, "max": 141, "coverage": 16.666666666666668, "n_users": 1}, {"region": "5279468", "min": 53, "max": 78, "coverage": 50.0, "n_users": 2}, {"region": "5279468", "min": 39, "max": 60, "coverage": 50.0, "n_users": 2}, {"region": "5037779", "min": 42, "max": 72, "coverage": 50.0, "n_users": 3}, {"region": "5037779", "min": 58, "max": 78, "coverage": 33.333333333333336, "n_users": 2}, {"region": "5037779", "min": 4, "max": 4, "coverage": 16.666666666666668, "n_users": 1}, {"region": "4862182", "min": 45, "max": 71, "coverage": 83.33333333333333, "n_users": 5}, {"region": "4862182", "min": 40, "max": 53, "coverage": 16.666666666666668, "n_users": 1}, {"region": "4482348", "min": 39, "max": 52, "coverage": 50.0, "n_users": 1}, {"region": "4482348", "min": 18, "max": 32, "coverage": 50.0, "n_users": 1}, {"region": "4155751", "min": 39, "max": 67, "coverage": 94.11764705882354, "n_users": 16}, {"region": "4155751", "min": 90, "max": 97, "coverage": 5.882352941176471, "n_users": 1}, {"region": "5128638", "min": 22, "max": 48, "coverage": 60.0, "n_users": 3}, {"region": "5128638", "min": 36, "max": 61, "coverage": 40.0, "n_users": 2}, {"region": "4896861", "min": 39, "max": 68, "coverage": 100.0, "n_users": 5}, {"region": "4829764", "min": 44, "max": 52, "coverage": 50.0, "n_users": 1}, {"region": "4829764", "min": 12, "max": 18, "coverage": 50.0, "n_users": 1}, {"region": "4826850", "min": 44, "max": 69, "coverage": 100.0, "n_users": 2}, {"region": "4273857", "min": 54, "max": 68, "coverage": 100.0, "n_users": 1}, {"region": "4099753", "min": 51, "max": 75, "coverage": 60.0, "n_users": 3}, {"region": "4099753", "min": 94, "max": 102, "coverage": 20.0, "n_users": 1}, {"region": "4099753", "min": 69, "max": 83, "coverage": 20.0, "n_users": 1}, {"region": "5165418", "min": 34, "max": 57, "coverage": 66.66666666666667, "n_users": 6}, {"region": "5165418", "min": 54, "max": 77, "coverage": 22.22222222222222, "n_users": 2}, {"region": "5165418", "min": 25, "max": 38, "coverage": 11.11111111111111, "n_users": 1}, {"region": "4662168", "min": 34, "max": 64, "coverage": 100.0, "n_users": 3}, {"region": "5001836", "min": 32, "max": 61, "coverage": 78.57142857142857, "n_users": 11}, {"region": "5001836", "min": 80, "max": 90, "coverage": 7.142857142857143, "n_users": 1}, {"region": "5001836", "min": 53, "max": 67, "coverage": 7.142857142857143, "n_users": 1}, {"region": "5001836", "min": 28, "max": 44, "coverage": 7.142857142857143, "n_users": 1}, {"region": "5843591", "min": 95, "max": 115, "coverage": 33.333333333333336, "n_users": 1}, {"region": "5843591", "min": 126, "max": 142, "coverage": 33.333333333333336, "n_users": 1}, {"region": "5843591", "min": 72, "max": 79, "coverage": 33.333333333333336, "n_users": 1}, {"region": "4138106", "min": 86, "max": 98, "coverage": 66.66666666666667, "n_users": 2}, {"region": "4138106", "min": 10, "max": 20, "coverage": 33.333333333333336, "n_users": 1}, {"region": "5551752", "min": 79, "max": 109, "coverage": 42.857142857142854, "n_users": 3}, {"region": "5551752", "min": 70, "max": 99, "coverage": 42.857142857142854, "n_users": 3}, {"region": "5551752", "min": 4, "max": 8, "coverage": 14.285714285714286, "n_users": 1}, {"region": "6254925", "min": 22, "max": 34, "coverage": 33.333333333333336, "n_users": 1}, {"region": "6254925", "min": 1, "max": 5, "coverage": 33.333333333333336, "n_users": 1}, {"region": "6254925", "min": 44, "max": 64, "coverage": 33.333333333333336, "n_users": 1}, {"region": "4971068", "min": 125, "max": 130, "coverage": 50.0, "n_users": 1}, {"region": "4971068", "min": 41, "max": 56, "coverage": 50.0, "n_users": 1}, {"region": "6254927", "min": 20, "max": 41, "coverage": 100.0, "n_users": 3}, {"region": "5481136", "min": 69, "max": 81, "coverage": 100.0, "n_users": 2}, {"region": "5417618", "min": 57, "max": 84, "coverage": 58.333333333333336, "n_users": 7}, {"region": "5417618", "min": 22, "max": 49, "coverage": 25.0, "n_users": 3}, {"region": "5417618", "min": 46, "max": 59, "coverage": 8.333333333333334, "n_users": 1}, {"region": "5417618", "min": 142, "max": 157, "coverage": 8.333333333333334, "n_users": 1}, {"region": "4361885", "min": 21, "max": 39, "coverage": 100.0, "n_users": 2}, {"region": "5101760", "min": 10, "max": 35, "coverage": 100.0, "n_users": 5}, {"region": "4331987", "min": 45, "max": 75, "coverage": 75.0, "n_users": 3}, {"region": "4331987", "min": 30, "max": 42, "coverage": 25.0, "n_users": 1}, {"region": "4043988", "min": 82, "max": 99, "coverage": 100.0, "n_users": 1}, {"region": "4197000", "min": 22, "max": 49, "coverage": 66.66666666666667, "n_users": 4}, {"region": "4197000", "min": 49, "max": 70, "coverage": 33.333333333333336, "n_users": 2}, {"region": "4736286", "min": 44, "max": 74, "coverage": 69.23076923076923, "n_users": 18}, {"region": "4736286", "min": 36, "max": 55, "coverage": 26.923076923076923, "n_users": 7}, {"region": "4736286", "min": 61, "max": 81, "coverage": 3.8461538461538463, "n_users": 1}, {"region": "5332921", "min": 76, "max": 101, "coverage": 65.0, "n_users": 13}, {"region": "5332921", "min": 70, "max": 98, "coverage": 15.0, "n_users": 3}, {"region": "5332921", "min": 40, "max": 54, "coverage": 5.0, "n_users": 1}, {"region": "5332921", "min": 62, "max": 81, "coverage": 5.0, "n_users": 1}, {"region": "5332921", "min": 115, "max": 144, "coverage": 5.0, "n_users": 1}, {"region": "5332921", "min": 23, "max": 28, "coverage": 5.0, "n_users": 1}, {"region": "4921868", "min": 39, "max": 65, "coverage": 80.0, "n_users": 4}, {"region": "4921868", "min": 32, "max": 45, "coverage": 20.0, "n_users": 1}], "last_updated": 1731888292.780299}